Metadata-Version: 2.1
Name: reqver
Version: 0.1.8
Summary: A tool to add version information to requirements.txt files
Home-page: https://github.com/Ralf12358/reqver
Author: Ralf Schneider
Author-email: ralf.schneider@example.com
Project-URL: Bug Reports, https://github.com/Ralf12358/reqver/issues
Project-URL: Source, https://github.com/Ralf12358/reqver/
Keywords: requirements version pip
Classifier: Development Status :: 3 - Alpha
Classifier: Intended Audience :: Developers
Classifier: Topic :: Software Development :: Build Tools
Classifier: Programming Language :: Python :: 3
Classifier: Programming Language :: Python :: 3.6
Classifier: Programming Language :: Python :: 3.7
Classifier: Programming Language :: Python :: 3.8
Classifier: Programming Language :: Python :: 3.9
Classifier: License :: OSI Approved :: MIT License
Classifier: Operating System :: OS Independent
Requires-Python: >=3.6
License-File: LICENSE
Requires-Dist: Click>=8.0.1
Requires-Dist: pip>=21.1.3
Requires-Dist: packaging>=20.0
